conda_forge_only/__init__.py
conda_forge_only/check.py
conda_forge_only/cli.py
conda_forge_only/version.py
conda_forge_only/tests/__init__.py
conda_forge_only/tests/test_check.py
conda_forge_only-0.1.0.dist-info/METADATA
conda_forge_only-0.1.0.dist-info/WHEEL
conda_forge_only-0.1.0.dist-info/entry_points.txt
conda_forge_only-0.1.0.dist-info/licenses/LICENSE.txt
conda_forge_only-0.1.0.dist-info/RECORD
