Metadata-Version: 2.3
Name: conda-forge-only
Version: 0.1.0
Summary: A pre-commit hook to check that conda environment files use conda-forge only.
Author-email: conda-forge-only developers <stephan.finkensieper@dwd.de>
Requires-Python: >=3.7
Requires-Dist: click
Requires-Dist: pyyaml
